dsds-0.0.34.dist-info/METADATA
dsds-0.0.34.dist-info/WHEEL
dsds-0.0.34.dist-info/license_files/LICENSE
dsds/blueprint.py
dsds/diagnosis.py
dsds/encoders.py
dsds/fs.py
dsds/metrics.py
dsds/optuna_integration.py
dsds/polars_extensions/expression_lib.py
dsds/polars_extensions/_dsds_rust.dll
dsds/polars_extensions/__init__.py
dsds/prescreen.py
dsds/sample.py
dsds/sklearn_compat_transfom.py
dsds/text.py
dsds/transform.py
dsds/type_alias.py
dsds/utils.py
dsds/__init__.py
dsds/_dsds_rust.cp311-win_amd64.pyd
dsds-0.0.34.dist-info/RECORD
