Metadata-Version: 2.1
Name: dsds
Version: 0.0.34
Classifier: Development Status :: 2 - Pre-Alpha
Classifier: Environment :: Console
Classifier: Intended Audience :: Science/Research
Classifier: License :: OSI Approved :: MIT License
Classifier: Operating System :: OS Independent
Classifier: Programming Language :: Rust
Classifier: Programming Language :: Python
Classifier: Programming Language :: Python :: 3
Classifier: Programming Language :: Python :: 3 :: Only
Classifier: Programming Language :: Python :: 3.9
Classifier: Programming Language :: Python :: 3.10
Classifier: Programming Language :: Python :: 3.11
Classifier: Topic :: Scientific/Engineering
Requires-Dist: polars >=0.19.9
Requires-Dist: scipy >=1.11.1
Requires-Dist: numpy
Requires-Dist: tqdm
Requires-Dist: pyarrow >=12.0
Requires-Dist: typing_extensions >=4.0.1
Requires-Dist: pytest >=7.4.1 ; extra == 'dev'
Requires-Dist: scikit-learn >=1.2.0 ; extra == 'dev'
Requires-Dist: pandas >=2.1 ; extra == 'dev'
Requires-Dist: category-encoders ; extra == 'dev'
Requires-Dist: optuna >=3.3 ; extra == 'tuning'
Requires-Dist: lightgbm >=4.1 ; extra == 'lgbm'
Requires-Dist: graphviz ; extra == 'plots'
Requires-Dist: lightgbm >=4.1 ; extra == 'fs'
Requires-Dist: optuna >=3.3 ; extra == 'fs'
Requires-Dist: lightgbm >=4.1 ; extra == 'all'
Requires-Dist: graphviz ; extra == 'all'
Requires-Dist: optuna >=3.3 ; extra == 'all'
Requires-Dist: data-pipeline ; extra == 'keywords'
Requires-Dist: EDA ; extra == 'keywords'
Requires-Dist: feature-screening ; extra == 'keywords'
Requires-Dist: feature-selection ; extra == 'keywords'
Provides-Extra: dev
Provides-Extra: tuning
Provides-Extra: lgbm
Provides-Extra: plots
Provides-Extra: fs
Provides-Extra: all
Provides-Extra: keywords
License-File: LICENSE
Author-email: Tianren Qin <tq9695@gmail.com>
Requires-Python: >=3.9
